gwpy/__init__.py
gwpy/_version.py
gwpy/conftest.py
gwpy/typing.py
gwpy/astro/__init__.py
gwpy/astro/range.py
gwpy/astro/tests/__init__.py
gwpy/astro/tests/test_range.py
gwpy/cli/__init__.py
gwpy/cli/cliproduct.py
gwpy/cli/coherence.py
gwpy/cli/coherencegram.py
gwpy/cli/gwpy_plot.py
gwpy/cli/qtransform.py
gwpy/cli/spectrogram.py
gwpy/cli/spectrum.py
gwpy/cli/timeseries.py
gwpy/cli/transferfunction.py
gwpy/cli/tests/__init__.py
gwpy/cli/tests/base.py
gwpy/cli/tests/test_coherence.py
gwpy/cli/tests/test_coherencegram.py
gwpy/cli/tests/test_gwpy_plot.py
gwpy/cli/tests/test_qtransform.py
gwpy/cli/tests/test_spectrogram.py
gwpy/cli/tests/test_spectrum.py
gwpy/cli/tests/test_timeseries.py
gwpy/cli/tests/test_transferfunction.py
gwpy/detector/__init__.py
gwpy/detector/channel.py
gwpy/detector/connect.py
gwpy/detector/tz.py
gwpy/detector/units.py
gwpy/detector/io/__init__.py
gwpy/detector/io/cis.py
gwpy/detector/io/clf.py
gwpy/detector/io/omega.py
gwpy/detector/tests/__init__.py
gwpy/detector/tests/test_channel.py
gwpy/detector/tests/test_tz.py
gwpy/detector/tests/test_units.py
gwpy/frequencyseries/__init__.py
gwpy/frequencyseries/_fdcommon.py
gwpy/frequencyseries/connect.py
gwpy/frequencyseries/frequencyseries.py
gwpy/frequencyseries/hist.py
gwpy/frequencyseries/io/__init__.py
gwpy/frequencyseries/io/ascii.py
gwpy/frequencyseries/io/hdf5.py
gwpy/frequencyseries/io/ligolw.py
gwpy/frequencyseries/tests/__init__.py
gwpy/frequencyseries/tests/test_frequencyseries.py
gwpy/frequencyseries/tests/test_hist.py
gwpy/io/__init__.py
gwpy/io/cache.py
gwpy/io/datafind.py
gwpy/io/ffldatafind.py
gwpy/io/hdf5.py
gwpy/io/kerberos.py
gwpy/io/ligolw.py
gwpy/io/nds2.py
gwpy/io/pelican.py
gwpy/io/registry.py
gwpy/io/remote.py
gwpy/io/root.py
gwpy/io/scitokens.py
gwpy/io/utils.py
gwpy/io/gwf/__init__.py
gwpy/io/gwf/backend.py
gwpy/io/gwf/core.py
gwpy/io/gwf/framecpp.py
gwpy/io/gwf/lalframe.py
gwpy/io/tests/__init__.py
gwpy/io/tests/test_cache.py
gwpy/io/tests/test_datafind.py
gwpy-4.0.0.dist-info/licenses/LICENSE
gwpy-4.0.0.dist-info/METADATA
gwpy-4.0.0.dist-info/WHEEL
gwpy-4.0.0.dist-info/entry_points.txt
gwpy-4.0.0.dist-info/top_level.txt
gwpy-4.0.0.dist-info/RECORD
